djangocms_bulma_content/__init__.py
djangocms_bulma_content/cms_plugins.py
djangocms_bulma_content/models.py
djangocms_bulma_content/migrations/0001_initial.py
djangocms_bulma_content/migrations/__init__.py
djangocms_bulma_content/templates/cms/plugins/djangocms-bulma-content.html
djangocms_bulma_content-0.1.1.dist-info/LICENSE
djangocms_bulma_content-0.1.1.dist-info/METADATA
djangocms_bulma_content-0.1.1.dist-info/WHEEL
djangocms_bulma_content-0.1.1.dist-info/top_level.txt
djangocms_bulma_content-0.1.1.dist-info/RECORD
